{
  "main": {
    "id": "4d0f5cf71525fec7",
    "type": "split",
    "children": [
      {
        "id": "92f3e643fc5b0eca",
        "type": "tabs",
        "children": [
          {
            "id": "e3b1696a52478828",
            "type": "leaf",
            "state": {
              "type": "markdown",
              "state": {
                "file": "2차(객체지향, 일반화 프로그래밍)/9장-Templates and Meta-Programming1/Type Traits/22. Type Trait Overview.md",
                "mode": "source",
                "source": false
              }
            }
          }
        ]
      }
    ],
    "direction": "vertical"
  },
  "left": {
    "id": "e9b4467b8377c8d3",
    "type": "split",
    "children": [
      {
        "id": "c6d143c68eae9ac0",
        "type": "tabs",
        "children": [
          {
            "id": "402363e53c464961",
            "type": "leaf",
            "state": {
              "type": "file-explorer",
              "state": {
                "sortOrder": "alphabetical"
              }
            }
          },
          {
            "id": "aeffe1214155763a",
            "type": "leaf",
            "state": {
              "type": "search",
              "state": {
                "query": "",
                "matchingCase": false,
                "explainSearch": false,
                "collapseAll": false,
                "extraContext": false,
                "sortOrder": "alphabetical"
              }
            }
          },
          {
            "id": "b820d72edfd41a52",
            "type": "leaf",
            "state": {
              "type": "bookmarks",
              "state": {}
            }
          }
        ]
      }
    ],
    "direction": "horizontal",
    "width": 217.5
  },
  "right": {
    "id": "7461ebc39c6f0acd",
    "type": "split",
    "children": [
      {
        "id": "6bfa24a3f6057506",
        "type": "tabs",
        "children": [
          {
            "id": "f6974c31d60d12c6",
            "type": "leaf",
            "state": {
              "type": "backlink",
              "state": {
                "file": "2차(객체지향, 일반화 프로그래밍)/9장-Templates and Meta-Programming1/Type Traits/22. Type Trait Overview.md",
                "collapseAll": false,
                "extraContext": false,
                "sortOrder": "alphabetical",
                "showSearch": false,
                "searchQuery": "",
                "backlinkCollapsed": false,
                "unlinkedCollapsed": true
              }
            }
          },
          {
            "id": "db710f2f2c02df57",
            "type": "leaf",
            "state": {
              "type": "outgoing-link",
              "state": {
                "file": "2차(객체지향, 일반화 프로그래밍)/9장-Templates and Meta-Programming1/Type Traits/22. Type Trait Overview.md",
                "linksCollapsed": false,
                "unlinkedCollapsed": true
              }
            }
          },
          {
            "id": "a1dc3a30c66bc036",
            "type": "leaf",
            "state": {
              "type": "tag",
              "state": {
                "sortOrder": "frequency",
                "useHierarchy": true
              }
            }
          },
          {
            "id": "175c97d284499522",
            "type": "leaf",
            "state": {
              "type": "outline",
              "state": {
                "file": "2차(객체지향, 일반화 프로그래밍)/9장-Templates and Meta-Programming1/Type Traits/22. Type Trait Overview.md"
              }
            }
          }
        ]
      }
    ],
    "direction": "horizontal",
    "width": 300,
    "collapsed": true
  },
  "left-ribbon": {
    "hiddenItems": {
      "switcher:퀵 스위처 열기": false,
      "graph:그래프 뷰 열기": false,
      "canvas:새 캔버스 만들기": false,
      "daily-notes:오늘의 데일리 노트 열기": false,
      "templates:템플릿 삽입": false,
      "command-palette:명령어 팔레트 열기": false
    }
  },
  "active": "e3b1696a52478828",
  "lastOpenFiles": [
    "2차(객체지향, 일반화 프로그래밍)/9장-Templates and Meta-Programming1/Function Template/21. Compile-Time Utilities.md",
    "2차(객체지향, 일반화 프로그래밍)/9장-Templates and Meta-Programming1/Type Traits/22. Type Trait Overview.md",
    "2차(객체지향, 일반화 프로그래밍)/9장-Templates and Meta-Programming1/Function Template/19. Template Parameter - Default Value, Overloading, Specialization.md",
    "2차(객체지향, 일반화 프로그래밍)/9장-Templates and Meta-Programming1/Function Template/20. Template Variable, Template Parameter Types.md",
    "2차(객체지향, 일반화 프로그래밍)/9장-Templates and Meta-Programming1/Function Template/18. Template Instantiation, Template Parameters.md",
    "2차(객체지향, 일반화 프로그래밍)/9장-Templates and Meta-Programming1/Function Template/17. Template Overview.md",
    "2차(객체지향, 일반화 프로그래밍)/TinyStudy-CPP-8장/16. C++ Layout. Standard-Layout Class, Plain Old Data.md",
    "2차(객체지향, 일반화 프로그래밍)/9장-Templates and Meta-Programming1/Function Template",
    "2차(객체지향, 일반화 프로그래밍)/9장-Templates and Meta-Programming1",
    "2차(객체지향, 일반화 프로그래밍)/9장. Templates and Meta-Programming1.md",
    "2차(객체지향, 일반화 프로그래밍)/TinyStudy-CPP-8장/15. C++ Layout. Aggregate, Trivial Class.md",
    "2차(객체지향, 일반화 프로그래밍)/TinyStudy-CPP-8장/14. Return Type Overloading Resolution, Increment and Decrement Operator, Assignment Operator, Stream Operator, Operator Notes.md",
    "2차(객체지향, 일반화 프로그래밍)/TinyStudy-CPP-8장/13. Overloading of Subscript, Function Call, static and Conversion Operator.md",
    "2차(객체지향, 일반화 프로그래밍)/TinyStudy-CPP-8장/12. Comparison Operator, Spaceship Operator.md",
    "1차/TinyStudy-CPP-2장/7. C++ Operators.md",
    "1차/TinyStudy-CPP-6장/43. Function Pointer and Function Object.md",
    "1차/TinyStudy-CPP-6장/48. Preprocessors.md",
    "1차/TinyStudy-CPP-6장/53. Token-Pasting Operator, Variadic Macro.md",
    "1차/TinyStudy-CPP-6장/51. Condition Compiling Macros.md",
    "1차/TinyStudy-CPP-6장/52. Stringizing Operator.md",
    "1차/TinyStudy-CPP-6장/47. nodiscard, Capture List and Classes.md",
    "1차/TinyStudy-CPP-6장/44. Capture List(Lambda Expression).md",
    "1차/TinyStudy-CPP-6장/45. Parameters, Composability, constexpr vs consteval.md",
    "1차/TinyStudy-CPP-6장/41. Function Signature and Overloading, Overloading and =delete.md",
    "1차/TinyStudy-CPP-6장/42. Default Parameter, Attributes.md",
    "1차/TinyStudy-CPP-6장/40. Pass by Value, Pass by Pointer and Pass by Reference.md",
    "2차(객체지향, 일반화 프로그래밍)/TinyStudy-CPP-8장/11. Inheritance Casting and Run-time Type Identification.md",
    "2차(객체지향, 일반화 프로그래밍)/TinyStudy-CPP-8장/10. override, final, pure virtual method, abstract class and interface .md",
    "2차(객체지향, 일반화 프로그래밍)/TinyStudy-CPP-8장",
    "2차(객체지향, 일반화 프로그래밍)/7장-Object-Oriented Programming 1",
    "2차(객체지향, 일반화 프로그래밍)",
    "1차",
    "1차/TinyStudy-CPP-5장"
  ]
}